pytojs/__init__.py
pytojs/base.py
pytojs/evaljs.py
pytojs/node_import.py
pytojs/pyjs.py
pytojs/constructors/__init__.py
pytojs/constructors/jsarray.py
pytojs/constructors/jsarraybuffer.py
pytojs/constructors/jsboolean.py
pytojs/constructors/jsdate.py
pytojs/constructors/jsfloat32array.py
pytojs/constructors/jsfloat64array.py
pytojs/constructors/jsfunction.py
pytojs/constructors/jsint16array.py
pytojs/constructors/jsint32array.py
pytojs/constructors/jsint8array.py
pytojs/constructors/jsmath.py
pytojs/constructors/jsnumber.py
pytojs/constructors/jsobject.py
pytojs/constructors/jsregexp.py
pytojs/constructors/jsstring.py
pytojs/constructors/jsuint16array.py
pytojs/constructors/jsuint32array.py
pytojs/constructors/jsuint8array.py
pytojs/constructors/jsuint8clampedarray.py
pytojs/constructors/time_helpers.py
pytojs/es6/__init__.py
pytojs/es6/babel.py
pytojs/host/__init__.py
pytojs/host/console.py
pytojs/host/jseval.py
pytojs/host/jsfunctions.py
pytojs/internals/__init__.py
pytojs/internals/base.py
pytojs/internals/byte_trans.py
pytojs/internals/code.py
pytojs/internals/conversions.py
pytojs/internals/desc.py
pytojs/internals/fill_space.py
pytojs/internals/func_utils.py
pytojs/internals/gen.py
pytojs/internals/opcodes.py
pytojs/internals/operations.py
pytojs/internals/seval.py
pytojs/internals/simplex.py
pytojs/internals/space.py
pytojs/internals/speed.py
pytojs/internals/trans_utils.py
pytojs/internals/constructors/__init__.py
pytojs/internals/constructors/jsarray.py
pytojs/internals/constructors/jsboolean.py
pytojs/internals/constructors/jsconsole.py
pytojs/internals/constructors/jsdate.py
pytojs/internals/constructors/jsfunction.py
pytojs/internals/constructors/jsmath.py
pytojs/internals/constructors/jsnumber.py
pytojs/internals/constructors/jsobject.py
pytojs/internals/constructors/jsregexp.py
pytojs/internals/constructors/jsstring.py
pytojs/internals/constructors/time_helpers.py
pytojs/internals/prototypes/__init__.py
pytojs/internals/prototypes/jsarray.py
pytojs-0.1.dist-info/LICENSE.md
pytojs-0.1.dist-info/METADATA
pytojs-0.1.dist-info/WHEEL
pytojs-0.1.dist-info/top_level.txt
pytojs-0.1.dist-info/RECORD
