Metadata-Version: 2.1
Name: pytojs
Version: 0.1
Summary: JavaScript to Python Translator & JavaScript interpreter written in 100% pure Python. (Fork from js2py)
Home-page: https://github.com/jo-project/pytojs
Author: jo-project
Author-email: jo.project.0911@gmail.com
License: MIT
License-File: LICENSE.md
Requires-Dist: tzlocal (>=1.2)
Requires-Dist: six (>=1.10)
Requires-Dist: pyjsparser (>=2.5.1)
